{
  "update_url": "https://clients2.google.com/service/update2/crx",
  "manifest_version": 2,
  "name": "Surebet calculator",
  "version": "1.0.0",
  "description": "With this surebet calculator you can check if some bet offer an arbitrage opportunity",
  "icons": {
    "128": "icons/icon128.png"
  },
  "browser_action": {
    "default_title": "Surebet calculator",
    "default_icon": "icons/icon128.png",
    "default_popup": "popup.html"
  },
  "web_accessible_resources": [
    "files/popup.js"
  ],
  "content_scripts": [
    {
      "js": [
        "popup.html"
      ],
      "matches": [
        "http://*/"
      ]
    }
  ],
  "permissions": [
    "tabs"
  ]
}
