{
  "update_url": "https://clients2.google.com/service/update2/crx",
  "description": "KindSafe is a safe-project internet project. We crawl websites and human-rate family unsafe content.",
  "name": "KindSafe.com",
  "permissions": [
    "https://www.kindsafe.com/*"
  ],
  "icons": {
    "48": "protect.png",
    "128": "protect.png"
  },
  "content_scripts": [
    {
      "matches": [
        "http://*/"
      ],
      "js": [
        "contentscript.js"
      ]
    }
  ],
  "manifest_version": 2,
  "version": "1.0.0"
}
