{
  "update_url": "https://clients2.google.com/service/update2/crx",
  "manifest_version": 2,
  "name": "CoinBlock",
  "shortname": "CoinBlock",
  "description": "CoinBlock blocks services like CoinHive from using your browser to mine cryptocurrency without your consent",
  "version": "0.10",
  "author": "Shmish <shmish90@gmail.com>",
  "icons": {
    "128": "icon/icon128.png",
    "48": "icon/icon48.png",
    "16": "icon/icon16.png"
  },
  "background": {
    "scripts": [
      "scripts/main.js",
      "scripts/store.js"
    ],
    "persistent": true
  },
  "browser_action": {
    "default_title": "CoinBlock",
    "default_popup": "markup/popup.html"
  },
  "permissions": [
    "storage",
    "webRequest",
    "webRequestBlocking",
    "tabs",
    "<all_urls>"
  ]
}
