{
  "update_url": "http://clients2.google.com/service/update2/crx",
  "name": "PoEsuna",
  "version": "1.0.0",
  "manifest_version": 2,
  "description": "Take a screenshot of item description from the website of Path of Exile.",
  "icons": {
    "16": "img/icon16.png",
    "48": "img/icon48.png",
    "128": "img/icon128.png"
  },
  "permissions": [
    "tabs",
    "storage",
    "http://www.pathofexile.com/",
    "https://www.pathofexile.com/"
  ],
  "content_security_policy": "script-src 'self' https://ssl.google-analytics.com; object-src 'self'",
  "content_scripts": [
    {
      "matches": [
        "http://www.pathofexile.com/*",
        "https://www.pathofexile.com/*"
      ],
      "js": [
        "js/jquery.min.js",
        "content.js"
      ]
    }
  ],
  "background": {
    "scripts": [
      "ga.js",
      "eventPage.js"
    ],
    "persistent": false
  },
  "options_page": "options.html"
}
