{
  "app": {
    "launch": {
      "web_url": "http://absolutist.com/online/bubbleshooter/chrome-bubbleshooter.html"
    },
    "urls": [
      "http://absolutist.com/online/bubbleshooter/chrome-bubbleshooter.html"
    ]
  },
  "default_locale": "en",
  "description": "__MSG_appDesc__",
  "icons": {
    "128": "bubble-shooter.png"
  },
  "manifest_version": 2,
  "name": "__MSG_appName__",
  "permissions": [
    "unlimitedStorage",
    "notifications"
  ],
  "update_url": "http://clients2.google.com/service/update2/crx",
  "version": "2.1"
}
