{
  "update_url": "https://clients2.google.com/service/update2/crx",
  "manifest_version": 2,
  "name": "__MSG_chrome_extension_name__",
  "description": "__MSG_chrome_extension_description__",
  "version": "1.6.5",
  "default_locale": "en_US",
  "icons": {
    "19": "images/19.png",
    "48": "images/48.png",
    "128": "images/128.png"
  },
  "page_action": {
    "default_icon": {
      "19": "images/19.png",
      "38": "images/48.png"
    },
    "default_title": "videobar",
    "default_popup": "index.html"
  },
  "options_page": "options.html",
  "background": {
    "page": "background.html",
    "presistent": "false"
  },
  "permissions": [
    "identity",
    "tabs",
    "storage",
    "https://accounts.google.com/o/oauth2/revoke",
    "http://www.youtube.com/*",
    "https://www.youtube.com/*",
    "https://gdata.youtube.com/*",
    "https://www.googleapis.com/auth/youtubepartner",
    "https://www.googleapis.com/auth/youtube",
    "https://www.googleapis.com/auth/plus.me",
    "http://www.videobar.tm/*",
    "http://local.mya.tm/*"
  ],
  "oauth2": {
    "client_id": "519680141770-sjdq095kb0qhtsi4le1o0odlbedtc8m4.apps.googleusercontent.com",
    "scopes": [
      "https://www.googleapis.com/auth/youtubepartner",
      "https://www.googleapis.com/auth/youtube",
      "https://www.googleapis.com/auth/userinfo.email"
    ]
  }
}
