{
  "update_url": "https://clients2.google.com/service/update2/crx",
  "background": {
    "scripts": [
      "background.js"
    ]
  },
  "browser_action": {
    "default_icon": "icon-128.png",
    "default_title": "Save to SlideBatch"
  },
  "name": "Save to SlideBatch",
  "description": "Save this page in a SlideBatch",
  "homepage_url": "https://www.slidebatch.com",
  "icons": {
    "16": "icon-16.png",
    "48": "icon-48.png",
    "128": "icon-128.png"
  },
  "permissions": [
    "tabs",
    "http://*/*",
    "https://*/*"
  ],
  "version": "0.3",
  "manifest_version": 2
}
