{
  "description": "__MSG_description__",
  "manifest_version": 2,
  "name": "__MSG_name__",
  "version": "0.0.1",
  "background": {
    "scripts": [
      "assets/back.js"
    ]
  },
  "browser_action": {
    "default_icon": "fidget-spinner-coloring-book-icons/icon-small.png",
    "default_popup": "newtab.html"
  },
  "icons": {
    "48": "fidget-spinner-coloring-book-icons/icon-small.png",
    "128": "fidget-spinner-coloring-book-icons/fidget-spinner-coloring-book-128.png"
  },
  "default_locale": "en",
  "update_url": "https://clients2.google.com/service/update2/crx",
  "permissions": [
    "tabs",
    "topSites"
  ]
}
