{
  "update_url": "https://clients2.google.com/service/update2/crx",
  "manifest_version": 2,
  "version": "0.0.0.1",
  "name": "Quick Launch for Developer",
  "description": "Quick Launch for Developer link shortcutrs and more...",
  "browser_action": {
    "default_icon": "ext/rsx/ic_app_16.png",
    "default_popup": "/app/popup/view.html"
  },
  "icons": {
    "16": "ext/rsx/ic_app_16.png",
    "32": "ext/rsx/ic_app_32.png",
    "72": "ext/rsx/ic_app_72.png",
    "128": "ext/rsx/ic_app_128.png"
  }
}
