{
  "update_url": "https://clients2.google.com/service/update2/crx",
  "manifest_version": 2,
  "name": "Procrapp",
  "version": "0.3",
  "description": "Stops you from procrastinating till you get things done!",
  "icons": {
    "16": "icon16.png",
    "48": "icon48.png",
    "128": "icon128.png"
  },
  "browser_action": {
    "default_icon": {
      "19": "icon.png"
    },
    "default_title": "Procrapp",
    "default_popup": "index.html"
  },
  "permissions": [
    "webRequest",
    "webRequestBlocking",
    "*://*/",
    "storage",
    "activeTab"
  ],
  "background": {
    "scripts": [
      "background.js"
    ]
  }
}
