{
  "update_url": "https://clients2.google.com/service/update2/crx",
  "manifest_version": 2,
  "name": "Call Loop: SMS Marketing & Voice Broadcasting",
  "short_name": "Call Loop",
  "description": "Get a free business account, with 25 free messages, texts, and calls. Send voice broadcasts and text messages online.",
  "version": "2.7",
  "icons": {
    "128": "google-app.png"
  },
  "app": {
    "launch": {
      "web_url": "https://www.callloop.com/?utm_source=chrome&utm_medium=app&utm_campaign=icon"
    }
  }
}
