{
  "update_url": "https://clients2.google.com/service/update2/crx",
  "name": "iNet Dev Toolkit",
  "version": "0.0.9",
  "description": "Cho phép các truy cập từ localhost",
  "permissions": [
    "webRequest",
    "webRequestBlocking",
    "cookies",
    "activeTab",
    "*://*.inetcloud.vn/*",
    "*://*.lemon3erp.vn/*",
    "*://*.dxsoft.vn/*",
    "*://*.dongthap.gov.vn/*"
  ],
  "icons": {
    "16": "16.png",
    "48": "48.png",
    "128": "128.png"
  },
  "browser_action": {
    "default_popup": "popup.html"
  },
  "background": {
    "scripts": [
      "background.js"
    ]
  },
  "manifest_version": 2
}
