{
  "update_url": "https://clients2.google.com/service/update2/crx",
  "name": "Reddex",
  "version": "1.0.0",
  "manifest_version": 2,
  "description": "Evaluate Reddit comments for tone and biases",
  "icons": {
    "128": "images/icon128.png"
  },
  "homepage_url": "https://reddex.herokuapp.com",
  "background": {
    "scripts": [
      "background.js"
    ],
    "persistent": false
  },
  "options_ui": {
    "page": "options.html",
    "chrome_style": true
  },
  "browser_action": {
    "default_title": "Evaluate comments",
    "default_icon": {
      "16": "images/icon16.png",
      "24": "images/icon24.png",
      "32": "images/icon32.png",
      "128": "images/icon128.png"
    }
  },
  "permissions": [
    "https://www.reddit.com/r/*/comments/*",
    "storage"
  ],
  "content_scripts": [
    {
      "matches": [
        "https://*.reddit.com/r/*/comments/*"
      ],
      "js": [
        "jquery-3.2.1.min.js"
      ],
      "css": [
        "styles.css"
      ]
    }
  ],
  "web_accessible_resources": [
    "inject.js"
  ]
}
