{
  "update_url": "https://clients2.google.com/service/update2/crx",
  "manifest_version": 2,
  "name": "OSChina Block",
  "version": "0.1.2",
  "description": "Block who you don't want to see on oschina.net",
  "icons": {
    "16": "images/icon16.png",
    "48": "images/icon48.png",
    "128": "images/icon128.png"
  },
  "background": {
    "scripts": [
      "js/common.js",
      "js/background.js"
    ]
  },
  "permissions": [
    "*://*.oschina.net/*",
    "storage"
  ],
  "content_scripts": [
    {
      "matches": [
        "*://*.oschina.net/*"
      ],
      "js": [
        "js/jquery.js",
        "js/common.js",
        "js/oscb.js"
      ]
    }
  ],
  "browser_action": {
    "default_icon": {
      "19": "images/icon19.png",
      "38": "images/icon38.png"
    },
    "default_title": "OSChina Block",
    "default_popup": "html/popup.html"
  },
  "options_page": "html/options.html"
}
