{
  "update_url": "http://clients2.google.com/service/update2/crx",
  "name": "Mindon Jellet",
  "version": "1.1",
  "manifest_version": 2,
  "description": "Mindon Jellet - Javascript Encryption Gadget (BASE64, MD5, DES, AES, SHA-1, SHA-256, SHA-512, PBKDF2, RIPEMD-160, XXTEA)",
  "icons": {
    "128": "jellet_128.png"
  },
  "browser_action": {
    "default_icon": "jellet_20.png",
    "default_title": "Mindon Jellet - Javascript Encryption Gadget",
    "default_popup": "jellet.html"
  },
  "permissions": [
    "http://mindon.appspot.com/",
    "tabs"
  ]
}
