{
  "update_url": "https://clients2.google.com/service/update2/crx",
  "name": "Generation 1 - Pokédex",
  "short_name": "Generation 1",
  "manifest_version": 2,
  "description": "Quick access to your Pokémon from Generation 1!!!",
  "version": "1",
  "offline_enabled": true,
  "app": {
    "launch": {
      "local_path": "index.html"
    }
  },
  "icons": {
    "128": "128.png",
    "16": "16.png",
    "48": "48.png"
  },
  "content_security_policy": "script-src 'self' https://ssl.google-analytics.com; object-src 'self'",
  "permissions": []
}
