{
  "update_url": "https://clients2.google.com/service/update2/crx",
  "manifest_version": 2,
  "name": "PDF to Image – Foxit Online",
  "short_name": "PDF to Image Converter",
  "description": "Convert PDF to JPG images online.",
  "version": "0.0.0.5",
  "icons": {
    "48": "icon48.png",
    "128": "icon128.png"
  },
  "app": {
    "urls": [
      "https://online.foxitsoftware.com/pdf-to-image?from=chrome-web-app-store"
    ],
    "launch": {
      "web_url": "https://online.foxitsoftware.com/pdf-to-image?from=chrome-web-app-store"
    }
  }
}
