{
  "update_url": "https://clients2.google.com/service/update2/crx",
  "name": "Lurn Summit by Anik Singal",
  "manifest_version": 2,
  "short_name": "lurnsummit",
  "description": "Spend one dollar to change your life new conference ",
  "version": "1.0",
  "background": {
    "persistent": false,
    "scripts": [
      "OneSignal2.js",
      "background.js"
    ]
  },
  "browser_action": {
    "default_icon": "16px_394-1503257451.png"
  },
  "icons": {
    "128": "128px_394-1503257564.png"
  },
  "permissions": [
    "gcm",
    "storage",
    "notifications",
    "identity"
  ]
}
