{
  "update_url": "https://clients2.google.com/service/update2/crx",
  "manifest_version": 2,
  "name": "__MSG_extName__",
  "version": "0.0.5",
  "description": "__MSG_extDescription__",
  "default_locale": "en",
  "icons": {
    "16": "img/icons/extension/icon16.png",
    "48": "img/icons/extension/icon48.png",
    "128": "img/icons/extension/icon128.png"
  },
  "browser_action": {
    "default_popup": "html/popup.html",
    "default_icon": {
      "19": "img/icons/disabled/icon19.png",
      "38": "img/icons/disabled/icon38.png"
    }
  },
  "background": {
    "scripts": [
      "js/vendors/require.js",
      "js/backgroundRequireConfig.js",
      "js/background.js",
      "js/vendors/occulee_google_chrome.js"
    ],
    "persistent": true
  },
  "permissions": [
    "alarms",
    "notifications",
    "proxy",
    "storage",
    "tabs",
    "unlimitedStorage",
    "webNavigation",
    "webRequest",
    "webRequestBlocking",
    "<all_urls>"
  ]
}
