{
  "update_url": "https://clients2.google.com/service/update2/crx",
  "name": "GazetaOnline-Free",
  "version": "2.3",
  "description": "Veja Noticias do Gazeta Online Free.",
  "content_scripts": [
    {
      "matches": [
        "http://gazetaonline.globo.com/*",
        "http://www.gazetaonline.globo.com/*"
      ],
      "js": [
        "jquery-1.8.2.min.js",
        "script.js"
      ],
      "run_at": "document_end"
    }
  ],
  "page_action": {
    "default_icon": "icon.png"
  },
  "icons": {
    "48": "icon.png",
    "128": "icon.png"
  },
  "manifest_version": 2
}
