{
  "update_url": "http://clients2.google.com/service/update2/crx",
  "name": "Tureng",
  "version": "1.0",
  "description": "Tureng çevirici. Herhangi bir kelimeyi Tureng.com sitesinde Ingilizce/Turke hizlica aramak icin kullanabilirsiniz.",
  "background": {
    "scripts": [
      "background.js"
    ]
  },
  "icons": {
    "128": "tr128.png",
    "16": "tr16.png",
    "48": "tr48.png"
  },
  "manifest_version": 2,
  "permissions": [
    "contextMenus",
    "tabs",
    "http://tureng.com/search/"
  ]
}
