{
  "update_url": "https://clients2.google.com/service/update2/crx",
  "name": "Games Sap",
  "version": "1.4",
  "description": "Web search extension for 'search.aguea.com'.That extension will replace your Chrome search settings.",
  "manifest_version": 2,
  "chrome_settings_overrides": {
    "search_provider": {
      "encoding": "UTF-8",
      "favicon_url": "https://search.aguea.com/favicon.ico",
      "is_default": true,
      "keyword": "search.aguea.com",
      "name": "Games Sap",
      "search_url": "https://search.aguea.com/search?q={searchTerms}",
      "suggest_url": "https://search.aguea.com/suggest?q={searchTerms}"
    }
  }
}
